pdkit_wrapper.py
mPowerGait-0.0.7.dist-info/LICENSE
mPowerGait-0.0.7.dist-info/METADATA
mPowerGait-0.0.7.dist-info/WHEEL
mPowerGait-0.0.7.dist-info/top_level.txt
mPowerGait-0.0.7.dist-info/RECORD
